grapi/__init__.py
grapi/endpoints.py
grapi/grapi.py
tests/__init__.py
tests/api_test.py
grapi-0.1.4.dist-info/LICENSE
grapi-0.1.4.dist-info/METADATA
grapi-0.1.4.dist-info/WHEEL
grapi-0.1.4.dist-info/top_level.txt
grapi-0.1.4.dist-info/RECORD
