Metadata-Version: 2.1
Name: grapi
Version: 0.1.4
Summary: Python 3 bindings for Graylog's REST API
Home-page: https://github.com/interputed/grapi
Author: Andrew Craighead
Author-email: craigheadap@missouri.edu
License: UNKNOWN
Keywords: graylog,graylog-api,graylog api,python3 graylog,python3 graylog api,python3 graylog-api
Platform: UNKNOWN
Classifier: Programming Language :: Python :: 3
Classifier: Operating System :: OS Independent
Classifier: Topic :: Software Development :: Libraries
